setup.py
tests/__init__.py
tests/test_thoonk_pubsub.py
tests/test_thoonk_types.py
txthoonk/__init__.py
txthoonk/client.py
txthoonk/types.py
txthoonk.egg-info/PKG-INFO
txthoonk.egg-info/SOURCES.txt
txthoonk.egg-info/dependency_links.txt
txthoonk.egg-info/requires.txt
txthoonk.egg-info/top_level.txt