Metadata-Version: 1.1
Name: txthoonk
Version: 0.1
Summary: Python/Twisted client for Thoonk
Home-page: https://github.com/Diginet/txthoonk
Author: Iuri Diniz
Author-email: iuridiniz@gmail.com
License: MIT
Download-URL: http://pypi.python.org/pypi/txthoonk
Keywords: Redis,Thoonk,Twisted
Platform: UNKNOWN
Classifier: Development Status :: 1 - Planning
Classifier: Environment :: Console
Classifier: Intended Audience :: Developers
Classifier: License :: OSI Approved :: MIT License
Classifier: Operating System :: OS Independent
Classifier: Programming Language :: Python :: 2.7
Classifier: Framework :: Twisted
